README.txt
setup.cfg
setup.py
jsonconfigfile/__init__.py
jsonconfigfile/config_test.py
jsonconfigfile.egg-info/PKG-INFO
jsonconfigfile.egg-info/SOURCES.txt
jsonconfigfile.egg-info/dependency_links.txt
jsonconfigfile.egg-info/requires.txt
jsonconfigfile.egg-info/top_level.txt