Metadata-Version: 1.1
Name: jsonconfigfile
Version: 1.0
Summary: Python package for importing configuration from a JSON file.
Home-page: https://github.com/Pipe-s/jsonconfigfile
Author: Luke Woydziak
Author-email: lwoydziak@gmail.com
License: UNKNOWN
Download-URL: https://github.com/Pipe-s/jsonconfigfile/tarball/1.0
Platform: any
Classifier: Development Status :: 3 - Alpha
Classifier: Natural Language :: English
Classifier: Operating System :: Unix
Classifier: Programming Language :: Python
Classifier: Programming Language :: Unix Shell
Classifier: Topic :: Software Development :: Libraries :: Python Modules
